lager/__about__.py
lager/__init__.py
lager/__main__.py
lager/const.py
lager/core.py
lager/dev.py
lager/fastapi.py
lager/logging/__init__.py
lager/py.typed
lager/pydantic.py
lager-0.20.1.dist-info/WHEEL
lager-0.20.1.dist-info/METADATA
lager-0.20.1.dist-info/RECORD
