Metadata-Version: 2.3
Name: lager
Version: 0.20.1
Summary: EZ-PZ logging based on loguru
Keywords: beer,dgi,dgpy,logging,loguru
Author: jesse rubin
Author-email: jesse rubin <jesse@dgi.com>
Classifier: Development Status :: 5 - Production/Stable
Classifier: Intended Audience :: Developers
Classifier: License :: OSI Approved :: MIT License
Classifier: Programming Language :: Python
Classifier: Programming Language :: Python :: 3 :: Only
Classifier: Programming Language :: Python :: 3.11
Classifier: Programming Language :: Python :: 3.12
Classifier: Programming Language :: Python :: 3.13
Classifier: Programming Language :: Python :: 3.14
Classifier: Typing :: Typed
Requires-Dist: loguru>=0.7
Requires-Dist: typing-extensions>=4.5,<5 ; python_full_version < '3.11'
Requires-Python: >=3.11, <4.0
